Metadata-Version: 1.1
Name: bugfreepy
Version: 0.0.3
Summary: add a text pic in your python file, but it is just for fun
Home-page: https://github.com/hey-bruce/bugfreepy
Author: BBruceyuan
Author-email: bruceyuan123@gmail.com
License: MIT
Platform: UNKNOWN
Classifier: Programming Language :: Python :: 3.5
Classifier: Programming Language :: Python :: 3.6
